insomniac/__init__.py
insomniac/__main__.py
insomniac/__version__.py
insomniac/action_get_my_profile_info.py
insomniac/actions_impl.py
insomniac/actions_providers.py
insomniac/actions_types.py
insomniac/activation.py
insomniac/counters_parser.py
insomniac/database_engine.py
insomniac/db_models.py
insomniac/device.py
insomniac/device_facade.py
insomniac/globals.py
insomniac/hardban_indicator.py
insomniac/limits.py
insomniac/migration.py
insomniac/navigation.py
insomniac/network.py
insomniac/params.py
insomniac/report.py
insomniac/safely_runner.py
insomniac/scroll_end_detector.py
insomniac/session.py
insomniac/session_state.py
insomniac/sessions.py
insomniac/sleeper.py
insomniac/softban_indicator.py
insomniac/storage.py
insomniac/typewriter.py
insomniac/utils.py
insomniac/validations.py
insomniac/views.py
insomniac/action_runners/__init__.py
insomniac/action_runners/actions_runners_manager.py
insomniac/action_runners/core.py
insomniac/action_runners/interact/__init__.py
insomniac/action_runners/interact/action_handle_blogger.py
insomniac/action_runners/interact/action_handle_hashtag.py
insomniac/action_runners/interact/action_handle_place.py
insomniac/action_runners/interact/action_handle_target.py
insomniac/action_runners/unfollow/__init__.py
insomniac/action_runners/unfollow/action_unfollow.py
insomniac/assets/ADBKeyboard-nomix.apk
insomniac/assets/ADBKeyboard.apk
insomniac/assets/aapt
insomniac/assets/gender_deploy.prototxt
insomniac/assets/gender_net.caffemodel
insomniac/extra_features/__init__.py
insomniac/extra_features/action_dm.py
insomniac/extra_features/action_handle_blogger_scrape.py
insomniac/extra_features/action_handle_hashtag_scrape.py
insomniac/extra_features/action_handle_place_scrape.py
insomniac/extra_features/action_manage_clones.py
insomniac/extra_features/action_register_accounts.py
insomniac/extra_features/action_remove_mass_followers.py
insomniac/extra_features/action_warmup.py
insomniac/extra_features/actions_impl.py
insomniac-3.9.0.dist-info/LICENSE
insomniac-3.9.0.dist-info/METADATA
insomniac-3.9.0.dist-info/WHEEL
insomniac-3.9.0.dist-info/top_level.txt
insomniac-3.9.0.dist-info/RECORD
