Metadata-Version: 2.1
Name: insomniac
Version: 3.9.0
Summary: Insomniac: Instagram bot for automated Instagram interaction using Android device via ADB
Home-page: https://github.com/alexal1/Insomniac
Author: Insomniac Team
Author-email: info@insomniac-bot.com
Classifier: Programming Language :: Python :: 3
Classifier: Operating System :: OS Independent
Requires-Python: >=3.6
License-File: LICENSE
Requires-Dist: uiautomator2
Requires-Dist: uiautomator
Requires-Dist: colorama
Requires-Dist: croniter
Requires-Dist: peewee
Requires-Dist: psycopg2-binary
Requires-Dist: Pillow
